adloc/__init__.py
adloc/_ransac.py
adloc/adloc.py
adloc/data.py
adloc/eikonal2d.py
adloc/eikonal3d.py
adloc/gmpe.py
adloc/inversion.py
adloc/sacloc2d.py
adloc/sacloc3d.py
adloc/test_grad.py
adloc/utils.py
adloc-1.0.3.dist-info/METADATA
adloc-1.0.3.dist-info/WHEEL
adloc-1.0.3.dist-info/top_level.txt
adloc-1.0.3.dist-info/RECORD
