Metadata-Version: 2.1
Name: ADLoc
Version: 1.0.3
Requires-Dist: numpy
Requires-Dist: h5py
Requires-Dist: matplotlib
Requires-Dist: pandas
Requires-Dist: tqdm
Requires-Dist: pyproj
Requires-Dist: numba
Requires-Dist: scipy
